sem/__init__.py
sem/manager.py
sem/re_patterns.py
sem/str_to_type.py
sem/structure_parsing.py
scientific_experiment_manager-0.1.0.dist-info/LICENSE
scientific_experiment_manager-0.1.0.dist-info/METADATA
scientific_experiment_manager-0.1.0.dist-info/WHEEL
scientific_experiment_manager-0.1.0.dist-info/top_level.txt
scientific_experiment_manager-0.1.0.dist-info/RECORD
