Metadata-Version: 2.1
Name: scientific-experiment-manager
Version: 0.1.0
Summary: SEM: streamline your scientific experiment management
Author: Nicolò Ruggeri
Author-email: nicolo.ruggeri@tuebingen.mpg.de
License: MIT
Project-URL: Source, https://github.com/nickruggeri/scientific-experiment-manager
Project-URL: Documentation, https://github.com/nickruggeri/scientific-experiment-manager
License-File: LICENSE
Requires-Dist: numpy (>=1.23.0)
Requires-Dist: pandas (>=1.5.0)
